wyseos/__init__.py
wyseos/mate/__init__.py
wyseos/mate/client.py
wyseos/mate/config.py
wyseos/mate/constants.py
wyseos/mate/errors.py
wyseos/mate/models.py
wyseos/mate/plan.py
wyseos/mate/websocket.py
wyseos/mate/services/__init__.py
wyseos/mate/services/agent.py
wyseos/mate/services/browser.py
wyseos/mate/services/file_upload.py
wyseos/mate/services/session.py
wyseos/mate/services/team.py
wyseos/mate/services/user.py
wyseos_sdk-0.2.1.dist-info/licenses/LICENSE
wyseos_sdk-0.2.1.dist-info/METADATA
wyseos_sdk-0.2.1.dist-info/WHEEL
wyseos_sdk-0.2.1.dist-info/top_level.txt
wyseos_sdk-0.2.1.dist-info/RECORD
